<?xml version="1.0" encoding="utf-8" ?>
<dwsync>
<file name="attributes.php" server="173.201.216.78//zhabchi/" local="130588886173480238" remote="130585927800000000" Dst="1" />
<file name="adminattributes.php" server="173.201.216.78//zhabchi/" local="130588886173490244" remote="130585927800000000" Dst="1" />
<file name="bounces.php" server="173.201.216.78//zhabchi/" local="130588886173555292" remote="130585927800000000" Dst="1" />
<file name="configure.php" server="173.201.216.78//zhabchi/" local="130588886193463936" remote="130585927800000000" Dst="1" />
<file name="community.php" server="173.201.216.78//zhabchi/" local="130588886193473943" remote="130585927800000000" Dst="1" />
<file name="defaults.php" server="173.201.216.78//zhabchi/" local="130588886193533983" remote="130585927800000000" Dst="1" />
<file name="eventlog.php" server="173.201.216.78//zhabchi/" local="130588886210555316" remote="130585927800000000" Dst="1" />
<file name="export.php" server="173.201.216.78//zhabchi/" local="130588886210565327" remote="130585927800000000" Dst="1" />
<file name="getrss.php" server="173.201.216.78//zhabchi/" local="130588886210645381" remote="130585927800000000" Dst="1" />
<file name="import1.php" server="173.201.216.78//zhabchi/" local="130588886227547293" remote="130585927800000000" Dst="1" />
<file name="import.php" server="173.201.216.78//zhabchi/" local="130588886227547293" remote="130585927800000000" Dst="1" />
<file name="import2.php" server="173.201.216.78//zhabchi/" local="130588886227587307" remote="130585927800000000" Dst="1" />
<file name="login.php" server="173.201.216.78//zhabchi/" local="130588886242888159" remote="130585927800000000" Dst="1" />
<file name="importadmin.php" server="173.201.216.78//zhabchi/" local="130588886242893167" remote="130585927800000000" Dst="1" />
<file name="logout.php" server="173.201.216.78//zhabchi/" local="130588886242913197" remote="130585927800000000" Dst="1" />
<file name="members.php" server="173.201.216.78//zhabchi/" local="130588886261915690" remote="130585927800000000" Dst="1" />
<file name="message.php" server="173.201.216.78//zhabchi/" local="130588886261915690" remote="130585927800000000" Dst="1" />
<file name="messages.php" server="173.201.216.78//zhabchi/" local="130588886262285941" remote="130585927800000000" Dst="1" />
<file name="reconcileusers.php" server="173.201.216.78//zhabchi/" local="130588886283461311" remote="130585927800000000" Dst="1" />
<file name="send.php" server="173.201.216.78//zhabchi/" local="130588886283471317" remote="130585927800000000" Dst="1" />
<file name="setup.php" server="173.201.216.78//zhabchi/" local="130588886283551362" remote="130585927800000000" Dst="1" />
<file name="spage.php" server="173.201.216.78//zhabchi/" local="130588886302313878" remote="130585927800000000" Dst="1" />
<file name="spageedit.php" server="173.201.216.78//zhabchi/" local="130588886302323889" remote="130585927800000000" Dst="1" />
<file name="statsmgt.php" server="173.201.216.78//zhabchi/" local="130588886302423948" remote="130585927800000000" Dst="1" />
<file name="templates.php" server="173.201.216.78//zhabchi/" local="130588886323697259" remote="130585927800000000" Dst="1" />
<file name="usermgt.php" server="173.201.216.78//zhabchi/" local="130588886323707270" remote="130585927800000000" Dst="1" />
<file name="vote.php" server="173.201.216.78//zhabchi/" local="130588886323817339" remote="130585927800000000" Dst="1" />
</dwsync>